[
{
  "My_id": [
    "watpure","novia","nico","ava","peterpan","sue","chuck","vance","cloe",
    "jay","annabelle","marco","lamber","silvia","amanda","ellyc",
    "cemily","joe","nicky","frank","tmeng","annies","tinay","joyce"
    ,"vernaL","alisonl","bess","arielh","jeffs"
  ],
  "Store_adr": [
    {
      "test":"img/anniversary/anniversary.jpg",
      "sjeff":"img/anniversary/anniversary.jpg",
      "skmtps":"img/anniversary/anniversary.jpg",
      "febc":"img/anniversary/anniversary.jpg",
      "chhola":"img/anniversary/anniversary.jpg",
      "dhouse":"img/anniversary/anniversary.jpg",
      "clhola":"img/anniversary/anniversary.jpg",
      "skmhsinchu":"img/anniversary/anniversary.jpg",
      "mlhola":"img/anniversary/anniversary.jpg",
      "skmcg":"img/anniversary/anniversary.jpg",
      "tchola":"img/anniversary/anniversary.jpg",
      "skmsm":"img/anniversary/anniversary.jpg",
      "zdhola":"img/anniversary/anniversary.jpg",
      "ktunite":"img/anniversary/anniversary.jpg",
      "skmsd":"img/anniversary/anniversary.jpg",
      "zyhola":"img/anniversary/anniversary.jpg"
    }
  ]
}
]